keras_tqdm/__init__.py
keras_tqdm/tqdm_callback.py
keras_tqdm/tqdm_notebook_callback.py
keras_tqdm-2.0.1.dist-info/DESCRIPTION.rst
keras_tqdm-2.0.1.dist-info/METADATA
keras_tqdm-2.0.1.dist-info/RECORD
keras_tqdm-2.0.1.dist-info/WHEEL
keras_tqdm-2.0.1.dist-info/metadata.json
keras_tqdm-2.0.1.dist-info/top_level.txt
