Metadata-Version: 2.0
Name: keras-tqdm
Version: 2.0.1
Summary: Keras models with TQDM progress bars in Jupyter notebooks
Home-page: https://github.com/bstriner/keras-tqdm
Author: Ben Striner
Author-email: bstriner@gmail.com
License: MIT
Download-URL: https://github.com/bstriner/keras-tqdm/tarball/v2.0.1
Keywords: keras,tqdm,progress,progressbar,ipython,jupyter
Platform: UNKNOWN
Classifier: Intended Audience :: Developers
Classifier: License :: OSI Approved :: MIT License
Classifier: Programming Language :: Python :: 2
Classifier: Programming Language :: Python :: 3
Requires-Dist: Keras
Requires-Dist: tqdm
